{
  "Enums": [
    {
      "Name": "StrictCharacterSet",
      "HasOtherVariant": true
    },
    {
      "Name": "LevelJustificationValues",
      "AddFacets": [
        {
          "Name": "Start",
          "Value": "start",
          "Version": "Office2010"
        },
        {
          "Name": "End",
          "Value": "end",
          "Version": "Office2010"
        }
      ]
    }
  ],
  "Types": [
    {
      "ClassName": "RunPropertiesDefault",
      "HaveXmlnsFields": true,
      "HaveXmlOtherAttrs": true
    },
    {
      "ClassName": "Font",
      "ParentChoiceHasAny": true
    },
    {
      "ClassName": "Paragraph",
      "ParentChoiceHasAny": true
    },
    {
      "ClassName": "Run",
      "ParentChoiceHasAny": true
    },
    {
      "ClassName": "SpacingBetweenLines",
      "HaveXmlOtherAttrs": true
    }
  ]
}
